unika_agent/__init__.py
unika_agent/actions.py
unika_agent/runner.py
unika_agent/workflow.py
unika_agent-0.1.0.dist-info/METADATA
unika_agent-0.1.0.dist-info/WHEEL
unika_agent-0.1.0.dist-info/top_level.txt
unika_agent-0.1.0.dist-info/RECORD
