Metadata-Version: 2.4
Name: unika-agent
Version: 0.1.0
Summary: Agent logic for Unika
Requires-Python: >=3.13
Requires-Dist: unika-core
